Workbook

Sheet 📊 Resumen Ejecutivo
B2: ⚽ FUTBOLZONE — DASHBOARD EJECUTIVO DE AVANCE DEL PROYECTO
B4: Programa: Análisis y Desarrollo de Software (ADSO) | SENA Trimestre III | Avance Actual: 75% MVP
B6: ='📋 Backlog General'!C4 | D6: ='👤 Historias CLIENTE'!C4 | E6: ='👑 Historias ADMIN'!C4 | F6: ='📋 Backlog General'!I4 | H6: ='📋 Backlog General'!E4
B8: TOTAL HISTORIAS (38 HUs Planificadas) | D8: HU CLIENTE (20 HUs (75% Listas)) | E8: HU ADMIN (18 HUs (77% Listas)) | F8: PUNTOS DESARROLLADOS (Puntos de Historia Listos) | H8: % AVANCE PROYECTO (Fase MVP Completada)
B10: 📌 ESTADO DE AVANCE POR MÓDULOS DEL SISTEMA
B11: Módulo / Área del Sistema | C11: Rol Destinatario | D11: Total HUs | E11: Completadas | F11: Pendientes | G11: % Avance Módulo | H11: Estado Actual
B12: Módulo 1: Autenticación, JWT & Gmail SMTP | C12: Todos | D12: =COUNTIF('📋 Backlog General'!E10:E47, "Autenticación") + COUNTIF('📋 Backlog General'!E10:E47, "Seguridad") | E12: =COUNTIFS('📋 Backlog General'!E10:E47, "Autenticación", '📋 Backlog General'!I10:I47, "Completado") + COUNTIFS('📋 Backlog General'!E10:E47, "Seguridad", '📋 Backlog General'!I10:I47, "Completado") | F12: =D12-E12 | G12: =E12/D12 | H12: 🟢 100% Funcional
B13: Módulo 2: Catálogo de Canchas & Filtros | C13: Cliente / Admin | D13: =COUNTIF('📋 Backlog General'!E10:E47, "Canchas") | E13: =COUNTIFS('📋 Backlog General'!E10:E47, "Canchas", '📋 Backlog General'!I10:I47, "Completado") | F13: =D13-E13 | G13: =E13/D13 | H13: 🟢 100% Funcional
B14: Módulo 3: Motor de Reservas & Disponibilidad | C14: Cliente / Admin | D14: =COUNTIF('📋 Backlog General'!E10:E47, "Reservas") + COUNTIF('📋 Backlog General'!E10:E47, "Agendamiento") | E14: =COUNTIFS('📋 Backlog General'!E10:E47, "Reservas", '📋 Backlog General'!I10:I47, "Completado") + COUNTIFS('📋 Backlog General'!E10:E47, "Agendamiento", '📋 Backlog General'!I10:I47, "Completado") | F14: =D14-E14 | G14: =E14/D14 | H14: 🟢 100% Funcional
B15: Módulo 4: Dashboard Admin, Personal & Reportes | C15: Administrador | D15: =COUNTIF('📋 Backlog General'!E10:E47, "Administración") + COUNTIF('📋 Backlog General'!E10:E47, "Personal") + COUNTIF('📋 Backlog General'!E10:E47, "Reportes") | E15: =COUNTIFS('📋 Backlog General'!E10:E47, "Administración", '📋 Backlog General'!I10:I47, "Completado") + COUNTIFS('📋 Backlog General'!E10:E47, "Personal", '📋 Backlog General'!I10:I47, "Completado") + COUNTIFS('📋 Backlog General'!E10:E47, "Reportes", '📋 Backlog General'!I10:I47, "Completado") | F15: =D15-E15 | G15: =E15/D15 | H15: 🟢 100% Funcional
B16: Módulo 5: UI/UX (Dock 3 Botones, Móvil & Tema) | C16: Todos | D16: =COUNTIF('📋 Backlog General'!E10:E47, "UI / UX") | E16: =COUNTIFS('📋 Backlog General'!E10:E47, "UI / UX", '📋 Backlog General'!I10:I47, "Completado") | F16: =D16-E16 | G16: =E16/D16 | H16: 🟢 100% Funcional
B17: Módulo 6: Torneos Deportivos | C17: Cliente / Admin | D17: =COUNTIF('📋 Backlog General'!E10:E47, "Torneos") | E17: =COUNTIFS('📋 Backlog General'!E10:E47, "Torneos", '📋 Backlog General'!I10:I47, "Completado") | F17: =D17-E17 | G17: =E17/D17 | H17: 🟡 75% Operativo
B18: Módulo 7: Pasarela de Pagos & Cloud (Fase Final) | C18: Todos | D18: =COUNTIF('📋 Backlog General'!E10:E47, "Pagos") + COUNTIF('📋 Backlog General'!E10:E47, "Comprobantes") + COUNTIF('📋 Backlog General'!E10:E47, "Notificaciones") + COUNTIF('📋 Backlog General'!E10:E47, "Fidelización") + COUNTIF('📋 Backlog General'!E10:E47, "Integraciones") + COUNTIF('📋 Backlog General'!E10:E47, "DevOps") | E18: 0 | F18: =D18 | G18: 0% | H18: ⏳ En Progreso
B19: TOTAL CONSOLIDADO DEL SISTEMA | C19: SISTEMA COMPLETO | D19: =SUM(D12:D18) | E19: =SUM(E12:E18) | F19: =SUM(F12:F18) | G19: =E19/D19 | H19: 🎯 75% MVP LISTO

Sheet 👤 Historias CLIENTE
B2: 👤 HISTORIAS DE USUARIO — MÓDULO CLIENTE & JUGADORES (75% AVANCE)
B4: Total HUs Cliente: | C4: =COUNTA(B10:B29) | D4: Completadas: | E4: =COUNTIF(H10:H29, "Completado") | F4: % Avance Cliente: | G4: =E4/C4 | H4: Puntos Totales: | I4: =SUM(F10:F29)
B9: ID | C9: Título de la Historia | D9: Módulo | E9: Prioridad | F9: Puntos | G9: Sprint | H9: Estado | I9: % Avance | J9: Descripción (Como / Quiero / Para) | K9: Endpoint API Backend | L9: Componente Frontend
B10: HU-01 | C10: Registro de Cuenta de Cliente | D10: Autenticación | E10: Alta | F10: 5 | G10: Sprint 1 | H10: Completado | I10: 100% | J10: Como visitante, quiero registrar mis datos con nombre, correo y clave, para tener una cuenta y reservar canchas. | K10: POST /api/usuarios/registro | L10: LoginModal.tsx
B11: HU-02 | C11: Inicio de Sesión con JWT | D11: Seguridad | E11: Alta | F11: 5 | G11: Sprint 1 | H11: Completado | I11: 100% | J11: Como cliente, quiero iniciar sesión con mi correo y contraseña, para acceder a mis reservas y perfil. | K11: POST /api/usuarios/login | L11: LoginModal.tsx
B12: HU-03 | C12: Recuperación de Contraseña con PIN Gmail | D12: Seguridad | E12: Alta | F12: 8 | G12: Sprint 1 | H12: Completado | I12: 100% | J12: Como cliente que olvidó su clave, quiero recibir un PIN de 6 dígitos en mi Gmail real, para restablecer mi acceso. | K12: POST /api/auth/recuperar-password/* | L12: RecuperarPasswordModal.tsx
B13: HU-04 | C13: Exploración del Catálogo de Canchas | D13: Canchas | E13: Alta | F13: 3 | G13: Sprint 2 | H13: Completado | I13: 100% | J13: Como cliente, quiero ver las canchas con fotos, tipo (F5, F7, F11), precios por hora y capacidad, para elegir mi cancha. | K13: GET /api/canchas/ | L13: Canchas.tsx
B14: HU-05 | C14: Filtrado Rápido por Tipo de Cancha | D14: Canchas | E14: Media | F14: 3 | G14: Sprint 2 | H14: Completado | I14: 100% | J14: Como cliente, quiero filtrar las canchas por botones píldora (Todas, F5, F7, F11), para encontrar rápido lo que busco. | K14: GET /api/canchas/?tipo=... | L14: Canchas.tsx
B15: HU-06 | C15: Consulta de Disponibilidad en Tiempo Real | D15: Agendamiento | E15: Alta | F15: 5 | G15: Sprint 2 | H15: Completado | I15: 100% | J15: Como cliente, quiero seleccionar una fecha en el calendario y ver qué horas están libres vs ocupadas, para planear mi partido. | K15: GET /api/canchas/{id}/disponibilidad | L15: ReservaModal.tsx
B16: HU-07 | C16: Creación y Agendamiento de Reserva | D16: Reservas | E16: Alta | F16: 8 | G16: Sprint 2 | H16: Completado | I16: 100% | J16: Como cliente autenticado, quiero seleccionar la cancha, fecha y horas, para apartar mi turno sin solapamientos. | K16: POST /api/reservas/ | L16: ReservaModal.tsx
B17: HU-08 | C17: Cálculo Automático de Tarifas | D17: Reservas | E17: Media | F17: 3 | G17: Sprint 2 | H17: Completado | I17: 100% | J17: Como cliente, quiero que el sistema calcule el costo según las horas y precio de la cancha, para saber el valor exacto. | K17: GET /api/canchas/{id} | L17: ReservaModal.tsx
B18: HU-09 | C18: Panel 'Mis Reservas' del Cliente | D18: Reservas | E18: Alta | F18: 5 | G18: Sprint 3 | H18: Completado | I18: 100% | J18: Como cliente, quiero ver la lista de mis partidos reservados con fecha, hora y estado, para llevar el control de mi agenda. | K18: GET /api/reservas/mis-reservas | L18: DashboardCliente.tsx
B19: HU-10 | C19: Cancelación de Turnos por el Cliente | D19: Reservas | E19: Media | F19: 5 | G19: Sprint 3 | H19: Completado | I19: 100% | J19: Como cliente, quiero cancelar una reserva que no pueda asistir, para liberar el horario a otros jugadores. | K19: DELETE /api/reservas/{id} | L19: DashboardCliente.tsx
B20: HU-11 | C20: Visualización de Torneos Disponibles | D20: Torneos | E20: Media | F20: 5 | G20: Sprint 3 | H20: Completado | I20: 100% | J20: Como cliente, quiero ver los torneos de la sede, categorías, fechas y premios, para enterarme de los campeonatos. | K20: GET /api/torneos/ | L20: Torneos.tsx
B21: HU-12 | C21: Inscripción de Equipo a Torneos | D21: Torneos | E21: Media | F21: 5 | G21: Sprint 3 | H21: Completado | I21: 100% | J21: Como capitán de equipo, quiero inscribir mi equipo en un torneo abierto, para competir por el trofeo y premio. | K21: POST /api/torneos/{id}/inscribir | L21: Torneos.tsx
... B29: HU-20 | C29: Sincronización con Google Calendar | D29: Integraciones | E29: Baja | F29: 3 | G29: Sprint 4 | H29: En Progreso | I29: 0% | J29: Como cliente, quiero un botón para añadir automáticamente el partido agendado a mi calendario de Google. | K29: Google Calendar API | L29: BotonCalendar.tsx

Sheet 👑 Historias ADMIN
B2: 👑 HISTORIAS DE USUARIO — MÓDULO ADMINISTRADOR & GESTIÓN (77% AVANCE)
B4: Total HUs Admin: | C4: =COUNTA(B10:B27) | D4: Completadas: | E4: =COUNTIF(H10:H27, "Completado") | F4: % Avance Admin: | G4: =E4/C4 | H4: Puntos Totales: | I4: =SUM(F10:F27)
B9: ID | C9: Título de la Historia | D9: Módulo | E9: Prioridad | F9: Puntos | G9: Sprint | H9: Estado | I9: % Avance | J9: Descripción (Como / Quiero / Para) | K9: Endpoint API Backend | L9: Componente Frontend
B10: HU-21 | C10: Panel de Control Principal (Dashboard Admin) | D10: Administración | E10: Alta | F10: 8 | G10: Sprint 1 | H10: Completado | I10: 100% | J10: Como administrador, quiero ver el resumen global de reservas, ingresos totales, usuarios y canchas activas en un panel. | K10: GET /api/reportes/resumen | L10: DashboardAdmin.tsx
B11: HU-22 | C11: Métricas Financieras e Ingresos en Tiempo Real | D11: Reportes | E11: Alta | F11: 5 | G11: Sprint 1 | H11: Completado | I11: 100% | J11: Como administrador, quiero consultar el dinero recaudado en el mes y proyecciones, para evaluar la rentabilidad. | K11: GET /api/reportes/resumen | L11: DashboardAdmin.tsx
B12: HU-23 | C12: Exportación de Reportes a Excel (.xlsx / .csv) | D12: Reportes | E12: Alta | F12: 5 | G12: Sprint 2 | H12: Completado | I12: 100% | J12: Como administrador, quiero descargar la base de datos de reservas e ingresos en formato Excel, para contabilidad física. | K12: Client Export / API | L12: DashboardAdmin.tsx
B13: HU-24 | C13: Creación y Registro de Nuevas Canchas | D13: Canchas | E13: Alta | F13: 5 | G13: Sprint 2 | H13: Completado | I13: 100% | J13: Como administrador, quiero agregar nuevas canchas con su tipo, capacidad, precio/hora y servicios, para ampliar la oferta. | K13: POST /api/canchas/ | L13: DashboardAdmin.tsx
B14: HU-25 | C14: Edición y Actualización de Tarifas de Canchas | D14: Canchas | E14: Alta | F14: 5 | G14: Sprint 2 | H14: Completado | I14: 100% | J14: Como administrador, quiero modificar los precios por hora y características de cada cancha, para ajustar promociones. | K14: PUT /api/canchas/{id} | L14: DashboardAdmin.tsx
B15: HU-26 | C15: Desactivación / Mantenimiento de Canchas | D15: Canchas | E15: Media | F15: 3 | G15: Sprint 2 | H15: Completado | I15: 100% | J15: Como administrador, quiero deshabilitar temporalmente una cancha en mantenimiento, para que los clientes no la reserven. | K15: PUT /api/canchas/{id} | L15: DashboardAdmin.tsx
B16: HU-27 | C16: Eliminación Segura de Canchas | D16: Canchas | E16: Baja | F16: 3 | G16: Sprint 2 | H16: Completado | I16: 100% | J16: Como administrador, quiero dar de baja canchas obsoletas con confirmación de seguridad. | K16: DELETE /api/canchas/{id} | L16: DashboardAdmin.tsx
B17: HU-28 | C17: Gestión Completa de Reservas Globales | D17: Reservas | E17: Alta | F17: 5 | G17: Sprint 3 | H17: Completado | I17: 100% | J17: Como administrador, quiero ver la lista de todas las reservas de todos los clientes con filtros por fecha y cancha. | K17: GET /api/reservas/ | L17: DashboardAdmin.tsx
B18: HU-29 | C18: Cambio de Estado de Reserva (Confirmar / Completar) | D18: Reservas | E18: Alta | F18: 5 | G18: Sprint 3 | H18: Completado | I18: 100% | J18: Como administrador, quiero marcar reservas como pagadas, completadas o canceladas al llegar los jugadores a la sede. | K18: PUT /api/reservas/{id}/estado | L18: DashboardAdmin.tsx
B19: HU-30 | C19: Registro y Alta de Empleados de la Sede | D19: Personal | E19: Alta | F19: 5 | G19: Sprint 3 | H19: Completado | I19: 100% | J19: Como administrador, quiero registrar empleados (Coordinadores, Mantenimiento, Seguridad, Atención), para ordenar el personal. | K19: POST /api/empleados/ | L19: DashboardAdmin.tsx
B20: HU-31 | C20: Listado y Edición del Personal | D20: Personal | E20: Media | F20: 3 | G20: Sprint 3 | H20: Completado | I20: 100% | J20: Como administrador, quiero consultar el teléfono, correo y cargo de cada empleado y editar sus datos. | K20: GET/PUT /api/empleados/ | L20: DashboardAdmin.tsx
B21: HU-32 | C21: Activación y Desactivación de Empleados | D21: Personal | E21: Media | F21: 3 | G21: Sprint 3 | H21: Completado | I21: 100% | J21: Como administrador, quiero desactivar empleados inactivos sin perder el registro histórico. | K21: PUT /api/empleados/{id} | L21: DashboardAdmin.tsx
... B27: HU-38 | C27: Módulo de Auditoría y Registro de Logs de Cambios | D27: Seguridad | E27: Baja | F27: 3 | G27: Sprint 4 | H27: En Progreso | I27: 0% | J27: Como administrador general, quiero ver qué empleado modificó una tarifa o canceló una reserva con fecha y hora. | K27: Tabla Auditoria DB | L27: LogsAuditoria.tsx

Sheet 📋 Backlog General
B2: 📋 MATRIZ GENERAL DE HISTORIAS DE USUARIO — AVANCE 75.0% (SENA ADSO III)
B4: Total HUs: | C4: =COUNTA(B10:B47) | D4: % Avance Global: | E4: =COUNTIF(I10:I47, "Completado")/C4 | F4: Puntos Totales: | G4: =SUM(G10:G47) | H4: Puntos Listos: | I4: =SUMIF(I10:I47, "Completado", G10:G47)
B9: ID | C9: Título de la Historia | D9: Rol Asignado | E9: Módulo | F9: Prioridad | G9: Puntos | H9: Sprint | I9: Estado | J9: % Avance | K9: Descripción de la Historia | L9: Endpoint API Backend | M9: Componente Frontend
B10: HU-01 | C10: Registro de Cuenta de Cliente | D10: Cliente | E10: Autenticación | F10: Alta | G10: 5 | H10: Sprint 1 | I10: Completado | J10: 100% | K10: Como visitante, quiero registrar mis datos con nombre, correo y clave, para tener una cuenta y reservar canchas. | L10: POST /api/usuarios/registro | M10: LoginModal.tsx
B11: HU-02 | C11: Inicio de Sesión con JWT | D11: Cliente | E11: Seguridad | F11: Alta | G11: 5 | H11: Sprint 1 | I11: Completado | J11: 100% | K11: Como cliente, quiero iniciar sesión con mi correo y contraseña, para acceder a mis reservas y perfil. | L11: POST /api/usuarios/login | M11: LoginModal.tsx
B12: HU-03 | C12: Recuperación de Contraseña con PIN Gmail | D12: Cliente | E12: Seguridad | F12: Alta | G12: 8 | H12: Sprint 1 | I12: Completado | J12: 100% | K12: Como cliente que olvidó su clave, quiero recibir un PIN de 6 dígitos en mi Gmail real, para restablecer mi acceso. | L12: POST /api/auth/recuperar-password/* | M12: RecuperarPasswordModal.tsx
B13: HU-04 | C13: Exploración del Catálogo de Canchas | D13: Cliente | E13: Canchas | F13: Alta | G13: 3 | H13: Sprint 2 | I13: Completado | J13: 100% | K13: Como cliente, quiero ver las canchas con fotos, tipo (F5, F7, F11), precios por hora y capacidad, para elegir mi cancha. | L13: GET /api/canchas/ | M13: Canchas.tsx
B14: HU-05 | C14: Filtrado Rápido por Tipo de Cancha | D14: Cliente | E14: Canchas | F14: Media | G14: 3 | H14: Sprint 2 | I14: Completado | J14: 100% | K14: Como cliente, quiero filtrar las canchas por botones píldora (Todas, F5, F7, F11), para encontrar rápido lo que busco. | L14: GET /api/canchas/?tipo=... | M14: Canchas.tsx
B15: HU-06 | C15: Consulta de Disponibilidad en Tiempo Real | D15: Cliente | E15: Agendamiento | F15: Alta | G15: 5 | H15: Sprint 2 | I15: Completado | J15: 100% | K15: Como cliente, quiero seleccionar una fecha en el calendario y ver qué horas están libres vs ocupadas, para planear mi partido. | L15: GET /api/canchas/{id}/disponibilidad | M15: ReservaModal.tsx
B16: HU-07 | C16: Creación y Agendamiento de Reserva | D16: Cliente | E16: Reservas | F16: Alta | G16: 8 | H16: Sprint 2 | I16: Completado | J16: 100% | K16: Como cliente autenticado, quiero seleccionar la cancha, fecha y horas, para apartar mi turno sin solapamientos. | L16: POST /api/reservas/ | M16: ReservaModal.tsx
B17: HU-08 | C17: Cálculo Automático de Tarifas | D17: Cliente | E17: Reservas | F17: Media | G17: 3 | H17: Sprint 2 | I17: Completado | J17: 100% | K17: Como cliente, quiero que el sistema calcule el costo según las horas y precio de la cancha, para saber el valor exacto. | L17: GET /api/canchas/{id} | M17: ReservaModal.tsx
B18: HU-09 | C18: Panel 'Mis Reservas' del Cliente | D18: Cliente | E18: Reservas | F18: Alta | G18: 5 | H18: Sprint 3 | I18: Completado | J18: 100% | K18: Como cliente, quiero ver la lista de mis partidos reservados con fecha, hora y estado, para llevar el control de mi agenda. | L18: GET /api/reservas/mis-reservas | M18: DashboardCliente.tsx
B19: HU-10 | C19: Cancelación de Turnos por el Cliente | D19: Cliente | E19: Reservas | F19: Media | G19: 5 | H19: Sprint 3 | I19: Completado | J19: 100% | K19: Como cliente, quiero cancelar una reserva que no pueda asistir, para liberar el horario a otros jugadores. | L19: DELETE /api/reservas/{id} | M19: DashboardCliente.tsx
B20: HU-11 | C20: Visualización de Torneos Disponibles | D20: Cliente | E20: Torneos | F20: Media | G20: 5 | H20: Sprint 3 | I20: Completado | J20: 100% | K20: Como cliente, quiero ver los torneos de la sede, categorías, fechas y premios, para enterarme de los campeonatos. | L20: GET /api/torneos/ | M20: Torneos.tsx
B21: HU-12 | C21: Inscripción de Equipo a Torneos | D21: Cliente | E21: Torneos | F21: Media | G21: 5 | H21: Sprint 3 | I21: Completado | J21: 100% | K21: Como capitán de equipo, quiero inscribir mi equipo en un torneo abierto, para competir por el trofeo y premio. | L21: POST /api/torneos/{id}/inscribir | M21: Torneos.tsx
... B47: HU-38 | C47: Módulo de Auditoría y Registro de Logs de Cambios | D47: Administrador | E47: Seguridad | F47: Baja | G47: 3 | H47: Sprint 4 | I47: En Progreso | J47: 0% | K47: Como administrador general, quiero ver qué empleado modificó una tarifa o canceló una reserva con fecha y hora. | L47: Tabla Auditoria DB | M47: LogsAuditoria.tsx
